kdd/__init__.py
kdd/kdd.py
kdd/kdd_manager.py
kdd-0.0.1.dist-info/METADATA
kdd-0.0.1.dist-info/WHEEL
kdd-0.0.1.dist-info/top_level.txt
kdd-0.0.1.dist-info/RECORD
