Metadata-Version: 2.1
Name: kdd
Version: 0.0.1
Summary: Helper package for easier management of order data
Home-page: UNKNOWN
Author: Arno De Donder
Author-email: arno@brainjar.ai
License: UNKNOWN
Platform: UNKNOWN
Classifier: Programming Language :: Python :: 3.8
Classifier: Programming Language :: Python :: 3.9
Classifier: Programming Language :: Python :: 3.10
Requires-Dist: pydantic
Requires-Dist: pandas
Requires-Dist: matplotlib
Requires-Dist: msgpack
Requires-Dist: pdf2image
